{
  "summary": {
    "total": 12,
    "ok": 12,
    "crash": 0,
    "timeout": 0,
    "missing": 0
  },
  "results": [
    {
      "path": "/home/cat/moss-rknn-codec-front-batch/codec_front_layer0_qkv.fp16.rk3576.rknn",
      "name": "codec_front_layer0_qkv.fp16.rk3576.rknn",
      "case": "codec_front_qkv",
      "pass_through": "auto",
      "input_shapes": [
        [
          1,
          4,
          256
        ]
      ],
      "input_dtypes": [
        "float32"
      ],
      "status": "OK",
      "load_ms": 0.667,
      "load_ret": 0,
      "init_ms": 127.541,
      "init_ret": 0,
      "phase": "inference",
      "infer_ms": 2.081,
      "outputs": [
        {
          "shape": [
            3,
            1,
            4,
            4,
            64
          ],
          "dtype": "float32",
          "finite": true,
          "min": -2.40625,
          "max": 2.599609375,
          "mean": -0.007285204250365496
        }
      ],
      "returncode": 0,
      "elapsed_ms": 1197.265,
      "stderr_tail": "W rknn-toolkit-lite2 version: 2.3.2\nW Query dynamic range failed. Ret code: RKNN_ERR_MODEL_INVALID. (If it is a static shape RKNN model, please ignore the above warning message.)\n"
    },
    {
      "path": "/home/cat/moss-rknn-codec-front-batch/codec_front_layer10_qkv.fp16.rk3576.rknn",
      "name": "codec_front_layer10_qkv.fp16.rk3576.rknn",
      "case": "codec_front_qkv",
      "pass_through": "auto",
      "input_shapes": [
        [
          1,
          32,
          256
        ]
      ],
      "input_dtypes": [
        "float32"
      ],
      "status": "OK",
      "load_ms": 0.997,
      "load_ret": 0,
      "init_ms": 132.81,
      "init_ret": 0,
      "phase": "inference",
      "infer_ms": 2.86,
      "outputs": [
        {
          "shape": [
            3,
            1,
            4,
            32,
            64
          ],
          "dtype": "float32",
          "finite": true,
          "min": -6.75,
          "max": 10.546875,
          "mean": 0.09169014543294907
        }
      ],
      "returncode": 0,
      "elapsed_ms": 1243.15,
      "stderr_tail": "W rknn-toolkit-lite2 version: 2.3.2\nW Query dynamic range failed. Ret code: RKNN_ERR_MODEL_INVALID. (If it is a static shape RKNN model, please ignore the above warning message.)\n"
    },
    {
      "path": "/home/cat/moss-rknn-codec-front-batch/codec_front_layer11_qkv.fp16.rk3576.rknn",
      "name": "codec_front_layer11_qkv.fp16.rk3576.rknn",
      "case": "codec_front_qkv",
      "pass_through": "auto",
      "input_shapes": [
        [
          1,
          32,
          256
        ]
      ],
      "input_dtypes": [
        "float32"
      ],
      "status": "OK",
      "load_ms": 1.069,
      "load_ret": 0,
      "init_ms": 131.598,
      "init_ret": 0,
      "phase": "inference",
      "infer_ms": 2.703,
      "outputs": [
        {
          "shape": [
            3,
            1,
            4,
            32,
            64
          ],
          "dtype": "float32",
          "finite": true,
          "min": -17.46875,
          "max": 16.171875,
          "mean": 0.14622072875499725
        }
      ],
      "returncode": 0,
      "elapsed_ms": 1260.162,
      "stderr_tail": "W rknn-toolkit-lite2 version: 2.3.2\nW Query dynamic range failed. Ret code: RKNN_ERR_MODEL_INVALID. (If it is a static shape RKNN model, please ignore the above warning message.)\n"
    },
    {
      "path": "/home/cat/moss-rknn-codec-front-batch/codec_front_layer1_qkv.fp16.rk3576.rknn",
      "name": "codec_front_layer1_qkv.fp16.rk3576.rknn",
      "case": "codec_front_qkv",
      "pass_through": "auto",
      "input_shapes": [
        [
          1,
          4,
          256
        ]
      ],
      "input_dtypes": [
        "float32"
      ],
      "status": "OK",
      "load_ms": 1.009,
      "load_ret": 0,
      "init_ms": 121.998,
      "init_ret": 0,
      "phase": "inference",
      "infer_ms": 2.232,
      "outputs": [
        {
          "shape": [
            3,
            1,
            4,
            4,
            64
          ],
          "dtype": "float32",
          "finite": true,
          "min": -1.8984375,
          "max": 1.7509765625,
          "mean": -0.033319029957056046
        }
      ],
      "returncode": 0,
      "elapsed_ms": 1247.858,
      "stderr_tail": "W rknn-toolkit-lite2 version: 2.3.2\nW Query dynamic range failed. Ret code: RKNN_ERR_MODEL_INVALID. (If it is a static shape RKNN model, please ignore the above warning message.)\n"
    },
    {
      "path": "/home/cat/moss-rknn-codec-front-batch/codec_front_layer2_qkv.fp16.rk3576.rknn",
      "name": "codec_front_layer2_qkv.fp16.rk3576.rknn",
      "case": "codec_front_qkv",
      "pass_through": "auto",
      "input_shapes": [
        [
          1,
          4,
          256
        ]
      ],
      "input_dtypes": [
        "float32"
      ],
      "status": "OK",
      "load_ms": 1.012,
      "load_ret": 0,
      "init_ms": 131.824,
      "init_ret": 0,
      "phase": "inference",
      "infer_ms": 1.953,
      "outputs": [
        {
          "shape": [
            3,
            1,
            4,
            4,
            64
          ],
          "dtype": "float32",
          "finite": true,
          "min": -2.755859375,
          "max": 3.009765625,
          "mean": 0.006332273129373789
        }
      ],
      "returncode": 0,
      "elapsed_ms": 1251.347,
      "stderr_tail": "W rknn-toolkit-lite2 version: 2.3.2\nW Query dynamic range failed. Ret code: RKNN_ERR_MODEL_INVALID. (If it is a static shape RKNN model, please ignore the above warning message.)\n"
    },
    {
      "path": "/home/cat/moss-rknn-codec-front-batch/codec_front_layer3_qkv.fp16.rk3576.rknn",
      "name": "codec_front_layer3_qkv.fp16.rk3576.rknn",
      "case": "codec_front_qkv",
      "pass_through": "auto",
      "input_shapes": [
        [
          1,
          4,
          256
        ]
      ],
      "input_dtypes": [
        "float32"
      ],
      "status": "OK",
      "load_ms": 0.96,
      "load_ret": 0,
      "init_ms": 127.667,
      "init_ret": 0,
      "phase": "inference",
      "infer_ms": 2.007,
      "outputs": [
        {
          "shape": [
            3,
            1,
            4,
            4,
            64
          ],
          "dtype": "float32",
          "finite": true,
          "min": -2.75,
          "max": 3.150390625,
          "mean": 0.023722797632217407
        }
      ],
      "returncode": 0,
      "elapsed_ms": 1245.913,
      "stderr_tail": "W rknn-toolkit-lite2 version: 2.3.2\nW Query dynamic range failed. Ret code: RKNN_ERR_MODEL_INVALID. (If it is a static shape RKNN model, please ignore the above warning message.)\n"
    },
    {
      "path": "/home/cat/moss-rknn-codec-front-batch/codec_front_layer4_qkv.fp16.rk3576.rknn",
      "name": "codec_front_layer4_qkv.fp16.rk3576.rknn",
      "case": "codec_front_qkv",
      "pass_through": "auto",
      "input_shapes": [
        [
          1,
          8,
          256
        ]
      ],
      "input_dtypes": [
        "float32"
      ],
      "status": "OK",
      "load_ms": 1.006,
      "load_ret": 0,
      "init_ms": 131.702,
      "init_ret": 0,
      "phase": "inference",
      "infer_ms": 2.699,
      "outputs": [
        {
          "shape": [
            3,
            1,
            4,
            8,
            64
          ],
          "dtype": "float32",
          "finite": true,
          "min": -3.525390625,
          "max": 4.18359375,
          "mean": 0.018590835854411125
        }
      ],
      "returncode": 0,
      "elapsed_ms": 1215.24,
      "stderr_tail": "W rknn-toolkit-lite2 version: 2.3.2\nW Query dynamic range failed. Ret code: RKNN_ERR_MODEL_INVALID. (If it is a static shape RKNN model, please ignore the above warning message.)\n"
    },
    {
      "path": "/home/cat/moss-rknn-codec-front-batch/codec_front_layer5_qkv.fp16.rk3576.rknn",
      "name": "codec_front_layer5_qkv.fp16.rk3576.rknn",
      "case": "codec_front_qkv",
      "pass_through": "auto",
      "input_shapes": [
        [
          1,
          8,
          256
        ]
      ],
      "input_dtypes": [
        "float32"
      ],
      "status": "OK",
      "load_ms": 0.963,
      "load_ret": 0,
      "init_ms": 128.167,
      "init_ret": 0,
      "phase": "inference",
      "infer_ms": 2.157,
      "outputs": [
        {
          "shape": [
            3,
            1,
            4,
            8,
            64
          ],
          "dtype": "float32",
          "finite": true,
          "min": -5.67578125,
          "max": 3.419921875,
          "mean": -0.052343446761369705
        }
      ],
      "returncode": 0,
      "elapsed_ms": 1258.169,
      "stderr_tail": "W rknn-toolkit-lite2 version: 2.3.2\nW Query dynamic range failed. Ret code: RKNN_ERR_MODEL_INVALID. (If it is a static shape RKNN model, please ignore the above warning message.)\n"
    },
    {
      "path": "/home/cat/moss-rknn-codec-front-batch/codec_front_layer6_qkv.fp16.rk3576.rknn",
      "name": "codec_front_layer6_qkv.fp16.rk3576.rknn",
      "case": "codec_front_qkv",
      "pass_through": "auto",
      "input_shapes": [
        [
          1,
          16,
          256
        ]
      ],
      "input_dtypes": [
        "float32"
      ],
      "status": "OK",
      "load_ms": 0.945,
      "load_ret": 0,
      "init_ms": 113.972,
      "init_ret": 0,
      "phase": "inference",
      "infer_ms": 2.455,
      "outputs": [
        {
          "shape": [
            3,
            1,
            4,
            16,
            64
          ],
          "dtype": "float32",
          "finite": true,
          "min": -4.19921875,
          "max": 5.21875,
          "mean": 0.05144939944148064
        }
      ],
      "returncode": 0,
      "elapsed_ms": 1235.528,
      "stderr_tail": "W rknn-toolkit-lite2 version: 2.3.2\nW Query dynamic range failed. Ret code: RKNN_ERR_MODEL_INVALID. (If it is a static shape RKNN model, please ignore the above warning message.)\n"
    },
    {
      "path": "/home/cat/moss-rknn-codec-front-batch/codec_front_layer7_qkv.fp16.rk3576.rknn",
      "name": "codec_front_layer7_qkv.fp16.rk3576.rknn",
      "case": "codec_front_qkv",
      "pass_through": "auto",
      "input_shapes": [
        [
          1,
          16,
          256
        ]
      ],
      "input_dtypes": [
        "float32"
      ],
      "status": "OK",
      "load_ms": 1.22,
      "load_ret": 0,
      "init_ms": 121.632,
      "init_ret": 0,
      "phase": "inference",
      "infer_ms": 2.548,
      "outputs": [
        {
          "shape": [
            3,
            1,
            4,
            16,
            64
          ],
          "dtype": "float32",
          "finite": true,
          "min": -3.3828125,
          "max": 2.697265625,
          "mean": 0.06159612536430359
        }
      ],
      "returncode": 0,
      "elapsed_ms": 1234.346,
      "stderr_tail": "W rknn-toolkit-lite2 version: 2.3.2\nW Query dynamic range failed. Ret code: RKNN_ERR_MODEL_INVALID. (If it is a static shape RKNN model, please ignore the above warning message.)\n"
    },
    {
      "path": "/home/cat/moss-rknn-codec-front-batch/codec_front_layer8_qkv.fp16.rk3576.rknn",
      "name": "codec_front_layer8_qkv.fp16.rk3576.rknn",
      "case": "codec_front_qkv",
      "pass_through": "auto",
      "input_shapes": [
        [
          1,
          32,
          256
        ]
      ],
      "input_dtypes": [
        "float32"
      ],
      "status": "OK",
      "load_ms": 0.977,
      "load_ret": 0,
      "init_ms": 130.802,
      "init_ret": 0,
      "phase": "inference",
      "infer_ms": 2.765,
      "outputs": [
        {
          "shape": [
            3,
            1,
            4,
            32,
            64
          ],
          "dtype": "float32",
          "finite": true,
          "min": -4.87109375,
          "max": 4.703125,
          "mean": 0.020481005311012268
        }
      ],
      "returncode": 0,
      "elapsed_ms": 1262.32,
      "stderr_tail": "W rknn-toolkit-lite2 version: 2.3.2\nW Query dynamic range failed. Ret code: RKNN_ERR_MODEL_INVALID. (If it is a static shape RKNN model, please ignore the above warning message.)\n"
    },
    {
      "path": "/home/cat/moss-rknn-codec-front-batch/codec_front_layer9_qkv.fp16.rk3576.rknn",
      "name": "codec_front_layer9_qkv.fp16.rk3576.rknn",
      "case": "codec_front_qkv",
      "pass_through": "auto",
      "input_shapes": [
        [
          1,
          32,
          256
        ]
      ],
      "input_dtypes": [
        "float32"
      ],
      "status": "OK",
      "load_ms": 1.122,
      "load_ret": 0,
      "init_ms": 117.492,
      "init_ret": 0,
      "phase": "inference",
      "infer_ms": 2.802,
      "outputs": [
        {
          "shape": [
            3,
            1,
            4,
            32,
            64
          ],
          "dtype": "float32",
          "finite": true,
          "min": -6.84765625,
          "max": 7.09765625,
          "mean": 0.1651269644498825
        }
      ],
      "returncode": 0,
      "elapsed_ms": 1289.952,
      "stderr_tail": "W rknn-toolkit-lite2 version: 2.3.2\nW Query dynamic range failed. Ret code: RKNN_ERR_MODEL_INVALID. (If it is a static shape RKNN model, please ignore the above warning message.)\n"
    }
  ]
}
